fena-8.0.0.data/scripts/fena.py
fena-8.0.0.dist-info/DESCRIPTION.rst
fena-8.0.0.dist-info/METADATA
fena-8.0.0.dist-info/RECORD
fena-8.0.0.dist-info/WHEEL
fena-8.0.0.dist-info/metadata.json
fena-8.0.0.dist-info/top_level.txt
fena_pyexpander/__init__.py
fena_pyexpander/expander3.py
fena_pyexpander/lib.py
fena_pyexpander/parser.py
fena_pyexpander/test.py
fena_pyexpander/test_rx.py
fenalib/__init__.py
fenalib/_nodes.py
fenalib/_nodes_original_order.py
fenalib/assert_utils.py
fenalib/command_builder.py
fenalib/config_data.py
fenalib/coord_utils.py
fenalib/general.py
fenalib/in_file_config.py
fenalib/interpreter.py
fenalib/lexer.py
fenalib/lexical_token.py
fenalib/logging_setup.py
fenalib/mcfunction.py
fenalib/node_visitors.py
fenalib/nodes.py
fenalib/number_utils.py
fenalib/parser.py
fenalib/pre_pyexpander.py
fenalib/repr_utils.py
fenalib/str_utils.py
fenalib/token_classes.py
fenalib/token_position.py
fenalib/writer.py
fenalib/config/blocks.json
fenalib/config/bossbar.json
fenalib/config/command_names.json
fenalib/config/config.ini
fenalib/config/dehash.py
fenalib/config/effects.json
fenalib/config/entities.json
fenalib/config/execute.json
fenalib/config/items.json
fenalib/config/particles.json
fenalib/config/replaceitem.json
fenalib/config/scoreboard.json
fenalib/config/selector.json
fenalib/config/team_options.json
