Metadata-Version: 2.0
Name: fena
Version: 8.0.0
Summary: Fena Preprocessor Language for Minecaft
Home-page: https://github.com/Aquafina-water-bottle/Fena
Author: Austin Siew
Author-email: glowing.locker@gmail.com
License: MIT
Keywords: minecaft language fena preprocessor
Platform: UNKNOWN
Classifier: Development Status :: 4 - Beta
Classifier: Natural Language :: English
Classifier: Programming Language :: Python :: 3.6
Classifier: License :: OSI Approved :: MIT License
